{"_mPlayer":[{"_mWeapon":{"_mIdamage":10,"_mCritRate":0,"_mCritDamage":0,"_mType":0,"_mClass":"","_mName":"Sword","_mUnique":true},"_mRole":{"_mId":2,"_mSprite":"../../../Content/Role/Player.txt"},"_mSummonBar":20,"_mExpToLevelUp":240.0,"_mSpeed":20,"_mSprite":"../../../Content/Role/Player.txt","_mHp":85.0,"_mHpMax":115.0,"_mMp":100.0,"_mMpMax":104.0,"_mIsDead":false,"_mName":"Jean","_mDodgeChance":0,"_mCritChance":10,"_mCritDamage":20,"_mLevel":2,"_mExp":200.0,"_mType":0,"_mAttackMoves":[{"_mType":0,"_mDamage":40,"_mName":"yo","_mMpCost":0,"_mIsAoe":false},{"_mType":0,"_mDamage":20,"_mName":"D:","_mMpCost":0,"_mIsAoe":false}],"_mMagicMoves":[{"_mType":0,"_mDamage":40,"_mName":"yo","_mMpCost":20,"_mIsAoe":false},{"_mType":0,"_mDamage":20,"_mName":"D:","_mMpCost":15,"_mIsAoe":false}],"_mTranform":{"_mCoordinates":{"_mX":0,"_mY":0},"_mSize":{"_mX":17,"_mY":10}}},{"_mWeapon":{"_mIdamage":10,"_mCritRate":0,"_mCritDamage":0,"_mType":0,"_mClass":"","_mName":"Knife","_mUnique":true},"_mRole":{"_mId":3,"_mSprite":"../../../Content/Role/Player.txt"},"_mSummonBar":30,"_mExpToLevelUp":240.0,"_mSpeed":20,"_mSprite":"../../../Content/Role/Player.txt","_mHp":100.0,"_mHpMax":115.0,"_mMp":100.0,"_mMpMax":104.0,"_mIsDead":false,"_mName":"Gojo","_mDodgeChance":100,"_mCritChance":10,"_mCritDamage":20,"_mLevel":2,"_mExp":200.0,"_mType":0,"_mAttackMoves":[{"_mType":0,"_mDamage":500,"_mName":"Purple","_mMpCost":0,"_mIsAoe":false}],"_mMagicMoves":[{"_mType":0,"_mDamage":250,"_mName":"Red","_mMpCost":50,"_mIsAoe":true},{"_mType":0,"_mDamage":200,"_mName":"Blue","_mMpCost":100,"_mIsAoe":false}],"_mTranform":{"_mCoordinates":{"_mX":0,"_mY":0},"_mSize":{"_mX":17,"_mY":10}}}],"_mItem":[{"_mIdamage":10,"_mCritRate":0,"_mCritDamage":0,"_mType":0,"_mClass":"","_mName":"Sword","_mUnique":true},{"_mIdamage":10,"_mCritRate":0,"_mCritDamage":0,"_mType":0,"_mClass":"","_mName":"Knife","_mUnique":true},{"_mName":"Potion","_mUnique":false},{"_mName":"Ether","_mUnique":false}],"_mItemNumber":[1,1,10,15],"_mCurrentZone":"Game"}